elliot_markitdown/__init__.py
elliot_markitdown-0.1.0.dist-info/LICENSE
elliot_markitdown-0.1.0.dist-info/METADATA
elliot_markitdown-0.1.0.dist-info/WHEEL
elliot_markitdown-0.1.0.dist-info/top_level.txt
elliot_markitdown-0.1.0.dist-info/RECORD
