Metadata-Version: 2.2
Name: elliot_markitdown
Version: 0.1.0
Summary: 一个文档处理和OCR工具包集合
Home-page: https://github.com/main2snipercc/markitdown-web----
Author: Elliot
Author-email: huang19911021@gmail.com
Classifier: Programming Language :: Python :: 3
Classifier: License :: OSI Approved :: MIT License
Classifier: Operating System :: OS Independent
Requires-Python: >=3.7
License-File: LICENSE
Requires-Dist: flask>=2.0.0
Requires-Dist: werkzeug>=2.0.0
Requires-Dist: requests>=2.26.0
Requires-Dist: PyMuPDF>=1.18.0
Requires-Dist: python-docx>=0.8.11
Requires-Dist: openpyxl>=3.0.7
Requires-Dist: python-pptx>=0.6.21
Requires-Dist: Pillow>=8.3.1
Requires-Dist: beautifulsoup4>=4.9.3
Requires-Dist: markdown>=3.3.4
Requires-Dist: python-magic>=0.4.24
Requires-Dist: python-magic-bin>=0.4.14; platform_system == "Windows"
Requires-Dist: openai>=1.0.0
Requires-Dist: pyautogui>=0.9.53
Requires-Dist: keyboard>=0.13.5
Requires-Dist: mss>=6.1.0
Requires-Dist: numpy>=1.21.0
Requires-Dist: opencv-python>=4.5.3.56
Requires-Dist: pytesseract>=0.3.8
Requires-Dist: pywin32>=223
Dynamic: author
Dynamic: author-email
Dynamic: classifier
Dynamic: description
Dynamic: description-content-type
Dynamic: home-page
Dynamic: requires-dist
Dynamic: requires-python
Dynamic: summary
